Unit01/GPI01/codes/excersice1/reg6.v
module reg6(
    output [5:0] o_data,
    output       o_overflow,
    output [5:0] feedback,

    input  [6:0]     sum,
    input            clk,
    input        i_rst_n

);
    //reg [5:0] data_reg;
    // always @(posedge clk or negedge i_rst_n) begin
    //     if (!i_rst_n)
    //         data_reg <= 6'b0;
    //     else
    //         data_reg <= sum[5:0];
    // end
    // Registro de 7 bits con reset asíncrono
    
    reg [5:0] data_reg;
    reg       overflow_reg;
    
    always @(posedge clk or negedge i_rst_n) begin
        if (!i_rst_n) begin
            data_reg     <= 6'b0;
            overflow_reg <= 1'b0;
        end else begin
            data_reg     <= sum[5:0];      // Guarda los 6 bits de datos
            overflow_reg <=   sum[6];      // Guarda el bit de overflow
        end
    end

    assign o_data     = data_reg;
    assign o_overflow = overflow_reg;
    assign feedback   = data_reg;      // Feedback del registro actual

endmodule

Unit01/GP01/codes/excersice1/mux2to1.v
module mux2to1_6b(
    output reg [5:0] o_mux,
    
    input [5:0] i_data1,
    input [5:0] i_data2,
    input [5:0] i_data,
    input [1:0] i_sel
);
    always @(*) begin
        case (i_sel)
            2'b00: o_mux = i_data2;
            2'b01: o_mux = i_data;
            2'b10: o_mux = i_data1;
            default: o_mux = 4'b0000;
        endcase
    end
endmodule

Unit01/GP01/codes/excersice1/adder_6b.v
module adder_6b(
    output [6:0] o_adder1,

    input  [3:0] i_data1,
    input  [5:0] i_data2 // feedback
);
    assign o_adder1 = {{3'b0}, i_data1} + {{1'b0}, i_data2};
endmodule

Unit01/GP01/codes/excersice1/adder_4b.v
module adder_4b(
    output [3:0] o_adder0,
    
    input  [2:0] i_data1,
    input  [2:0] i_data2
);
    assign o_adder0 = {1'b0, i_data1} + {1'b0, i_data2};
endmodule

Unit01/GP01/codes/excersice1/top.v
module top #(
    parameter NB_OUTPUT = 8,
    parameter NB_INPUT_DATA = 3,
    parameter NB_SELECT = 2
)(
    output [NB_OUTPUT-1:0] o_data,
    output o_overflow,
    input [NB_INPUT_DATA-1:0] i_data1,
    input [NB_INPUT_DATA-1:0] i_data2,
    input [NB_SELECT-1:0] i_sel,
    input clk,
    input i_rst_n
);

    wire [3:0] connectAdd4b_to_mux2to1;
    wire [5:0] connectMux2to1_to_add6b;
    wire [5:0] connectFeedbackReg_to_add6b;
    wire [6:0] connectAdd6b_to_reg;
    wire [5:0] connectData;
    
    //wire connectOverflow;
    wire [5:0] extended0, extended2;

    assign extended0 = {1'b0, i_data1};
    assign extended2 = {1'b0, i_data2};

    adder_4b u_adder_4b(
        .o_adder0(connectAdd4b_to_mux2to1),
        .i_data1(i_data1),
        .i_data2(i_data2)
    );

    adder_6b u_adder_6b(
        .o_adder1(connectAdd6b_to_reg),
        .i_data1(connectMux2to1_to_add6b),
        .i_data2(connectFeedbackReg_to_add6b)
    );

    mux2to1_6b u_mux2to1_6b(
        .o_mux(connectMux2to1_to_add6b),
        .i_data1(extended0),
        .i_data2(extended2),
        .i_data(connectAdd4b_to_mux2to1),
        .i_sel(i_sel)
    );

    reg6 u_reg6(
        .o_data(connectData),
        .o_overflow(connectOverflow),
        .feedback(connectFeedbackReg_to_add6b),
        .sum(connectAdd6b_to_reg),
        .clk(clk),
        .i_rst_n(i_rst_n)
    );

    assign o_data = connectData;
    //assign o_overflow = connectOverflow;
    assign o_overflow = connectAdd6b_to_reg[6];
    
endmodule

Unit01/GP01/codes/excersice1/tb_test2.v
`timescale 1ns/1ps

module tb_top;
    reg                     clk;
    reg                 i_rst_n;
    reg  [2:0] i_data1, i_data2;
    reg  [1:0]            i_sel;
    wire [5:0]           o_data;
    wire             o_overflow;
    
    top uut (
        .o_data         (o_data),
        .o_overflow (o_overflow),
        .i_data1       (i_data1),
        .i_data2       (i_data2),
        .i_sel           (i_sel),
        .clk               (clk),
        .i_rst_n       (i_rst_n)
    );
    
    always #5 clk = ~clk;
    
    initial begin
        clk     =       0;
        i_rst_n =       0;
        i_data1 = 4'b0001;
        i_data2 = 4'b0001;
        i_sel   =       1;
        
        #5 i_rst_n =    1;

        #330 $finish;
    end
    
always begin
    @(posedge clk); 
    i_data1 =       1;
    i_data2 =       1;
    i_sel   =  4'b001;
end

    initial begin
        $dumpfile("waveform.vcd");
        $dumpvars(0, tb_top);
        $monitor("Time=%t, i_data1=%d, i_data2=%d, i_sel=%b, o_data=%d, o_overflow=%b", 
                 $time, i_data1, i_data2, i_sel, o_data, o_overflow);
    end
endmodule

R/GP01/GP01.sim/sim_1/behav/xsim/waveform.vcd
$date
   Fri Nov 14 11:51:34 2025
$end

$version
  2025.1.0
  $dumpfile ("waveform.vcd") 
$end

$timescale
  1ps
$end

$scope module tb_top $end
$var reg 1 ! clk $end
$var reg 1 " i_rst_n $end
$var reg 3 # i_data1 [2:0] $end
$var reg 3 $ i_data2 [2:0] $end
$var reg 2 % i_sel [1:0] $end
$var wire 6 & o_data [5:0] $end
$var wire 1 ' o_overflow $end
$scope module uut $end
$var wire 8 ( o_data [7:0] $end
$var wire 1 ' o_overflow $end
$var wire 3 ) i_data1 [2:0] $end
$var wire 3 * i_data2 [2:0] $end
$var wire 2 + i_sel [1:0] $end
$var wire 1 , clk $end
$var wire 1 - i_rst_n $end
$var wire 4 . connectAdd4b_to_mux2to1 [3:0] $end
$var wire 6 / connectMux2to1_to_add6b [5:0] $end
$var wire 6 0 connectFeedbackReg_to_add6b [5:0] $end
$var wire 7 1 connectAdd6b_to_reg [6:0] $end
$var wire 6 2 connectData [5:0] $end
$var wire 6 3 extended0 [5:0] $end
$var wire 6 4 extended2 [5:0] $end
$var wire 1 5 connectOverflow $end
$scope module u_adder_4b $end
$var wire 4 . o_adder0 [3:0] $end
$var wire 3 ) i_data1 [2:0] $end
$var wire 3 * i_data2 [2:0] $end
$upscope $end
$scope module u_adder_6b $end
$var wire 7 1 o_adder1 [6:0] $end
$var wire 4 6 i_data1 [3:0] $end
$var wire 6 0 i_data2 [5:0] $end
$upscope $end
$scope module u_mux2to1_6b $end
$var reg 6 7 o_mux [5:0] $end
$var wire 6 3 i_data1 [5:0] $end
$var wire 6 4 i_data2 [5:0] $end
$var wire 6 8 i_data [5:0] $end
$var wire 2 + i_sel [1:0] $end
$upscope $end
$scope module u_reg6 $end
$var wire 6 2 o_data [5:0] $end
$var wire 1 5 o_overflow $end
$var wire 6 0 feedback [5:0] $end
$var wire 7 1 sum [6:0] $end
$var wire 1 , clk $end
$var wire 1 - i_rst_n $end
$var reg 6 9 data_reg [5:0] $end
$var reg 1 : overflow_reg $end
$upscope $end
$upscope $end
$upscope $end
$enddefinitions $end

#0
$dumpvars
0!
0"
b1 #
b1 $
b1 %
b0 &
0'
b0 (
b1 )
b1 *
b1 +
0,
0-
b10 .
bz0010 /
b0 0
b10 1
b0 2
b1 3
b1 4
05
b10 6
bz0010 7
bz0010 8
b0 9
0:
$end

#5000
1!
1"
b10 &
b10 (
1,
1-
b10 0
b100 1
b10 2
b10 9

#10000
0!
0,

#15000
1!
b100 &
b100 (
1,
b100 0
b110 1
b100 2
b100 9

#20000
0!
0,

#25000
1!
b110 &
b110 (
1,
b110 0
b1000 1
b110 2
b110 9

#30000
0!
0,

#35000
1!
b1000 &
b1000 (
1,
b1000 0
b1010 1
b1000 2
b1000 9

#40000
0!
0,

#45000
1!
b1010 &
b1010 (
1,
b1010 0
b1100 1
b1010 2
b1010 9

#50000
0!
0,

#55000
1!
b1100 &
b1100 (
1,
b1100 0
b1110 1
b1100 2
b1100 9

#60000
0!
0,

#65000
1!
b1110 &
b1110 (
1,
b1110 0
b10000 1
b1110 2
b1110 9

#70000
0!
0,

#75000
1!
b10000 &
b10000 (
1,
b10000 0
b10010 1
b10000 2
b10000 9

#80000
0!
0,

#85000
1!
b10010 &
b10010 (
1,
b10010 0
b10100 1
b10010 2
b10010 9

#90000
0!
0,

#95000
1!
b10100 &
b10100 (
1,
b10100 0
b10110 1
b10100 2
b10100 9

#100000
0!
0,

#105000
1!
b10110 &
b10110 (
1,
b10110 0
b11000 1
b10110 2
b10110 9

#110000
0!
0,

#115000
1!
b11000 &
b11000 (
1,
b11000 0
b11010 1
b11000 2
b11000 9

#120000
0!
0,

#125000
1!
b11010 &
b11010 (
1,
b11010 0
b11100 1
b11010 2
b11010 9

#130000
0!
0,

#135000
1!
b11100 &
b11100 (
1,
b11100 0
b11110 1
b11100 2
b11100 9

#140000
0!
0,

#145000
1!
b11110 &
b11110 (
1,
b11110 0
b100000 1
b11110 2
b11110 9

#150000
0!
0,

#155000
1!
b100000 &
b100000 (
1,
b100000 0
b100010 1
b100000 2
b100000 9

#160000
0!
0,

#165000
1!
b100010 &
b100010 (
1,
b100010 0
b100100 1
b100010 2
b100010 9

#170000
0!
0,

#175000
1!
b100100 &
b100100 (
1,
b100100 0
b100110 1
b100100 2
b100100 9

#180000
0!
0,

#185000
1!
b100110 &
b100110 (
1,
b100110 0
b101000 1
b100110 2
b100110 9

#190000
0!
0,

#195000
1!
b101000 &
b101000 (
1,
b101000 0
b101010 1
b101000 2
b101000 9

#200000
0!
0,

#205000
1!
b101010 &
b101010 (
1,
b101010 0
b101100 1
b101010 2
b101010 9

#210000
0!
0,

#215000
1!
b101100 &
b101100 (
1,
b101100 0
b101110 1
b101100 2
b101100 9

#220000
0!
0,

#225000
1!
b101110 &
b101110 (
1,
b101110 0
b110000 1
b101110 2
b101110 9

#230000
0!
0,

#235000
1!
b110000 &
b110000 (
1,
b110000 0
b110010 1
b110000 2
b110000 9

#240000
0!
0,

#245000
1!
b110010 &
b110010 (
1,
b110010 0
b110100 1
b110010 2
b110010 9

#250000
0!
0,

#255000
1!
b110100 &
b110100 (
1,
b110100 0
b110110 1
b110100 2
b110100 9

#260000
0!
0,

#265000
1!
b110110 &
b110110 (
1,
b110110 0
b111000 1
b110110 2
b110110 9

#270000
0!
0,

#275000
1!
b111000 &
b111000 (
1,
b111000 0
b111010 1
b111000 2
b111000 9

#280000
0!
0,

#285000
1!
b111010 &
b111010 (
1,
b111010 0
b111100 1
b111010 2
b111010 9

#290000
0!
0,

#295000
1!
b111100 &
b111100 (
1,
b111100 0
b111110 1
b111100 2
b111100 9

#300000
0!
0,

#305000
1!
b111110 &
1'
b111110 (
1,
b111110 0
b1000000 1
b111110 2
b111110 9

#310000
0!
0,

#315000
1!
b0 &
0'
b0 (
1,
b0 0
b10 1
b0 2
15
b0 9
1:

#320000
0!
0,

#325000
1!
b10 &
b10 (
1,
b10 0
b100 1
b10 2
05
b10 9
0:

